<graph xaxisname='Months' yaxisname='Page Hits' caption='Client Page Top Users' lineThickness='1' animation='1' showNames='1' alpha='100' showLimits='1' decimalPrecision='1' rotateNames='1' numDivLines='3' limitsDecimalPrecision='0' showValues='0'>
   <categories>
      <category name='Client 1' showName='1' />
   </categories>
   <dataset seriesName='User 1' color='0066CC'>
      <set value='810' alpha='100' />
   </dataset>
   <dataset seriesName='User 2' color='3384D6'>
      <set value='380' alpha='100' />
   </dataset>
   <dataset seriesName='User 3' color='66A3E0'>
      <set value='220' alpha='100' />
   </dataset>
   <dataset seriesName='User 4' color='99C1EA'>
      <set value='20' alpha='100' />
   </dataset>
   <dataset seriesName='User 5' color='CCE0F4'>
      <set value='10' alpha='100' />
   </dataset>
</graph>